S3.py
myutitlityshaurya-1.0.5.dist-info/METADATA
myutitlityshaurya-1.0.5.dist-info/WHEEL
myutitlityshaurya-1.0.5.dist-info/top_level.txt
myutitlityshaurya-1.0.5.dist-info/RECORD
